README.rst
setup.py
phtml/__init__.py
phtml/module_test.py
phtml.egg-info/PKG-INFO
phtml.egg-info/SOURCES.txt
phtml.egg-info/dependency_links.txt
phtml.egg-info/entry_points.txt
phtml.egg-info/requires.txt
phtml.egg-info/top_level.txt