Metadata-Version: 1.1
Name: phtml
Version: 0.0.1
Summary: Refactor HTML in Python
Home-page: https://github.com/yourlabs/phtml
Author: James Pic
Author-email: jamespic@gmail.com
License: MIT
Keywords: html
Platform: UNKNOWN
Classifier: Development Status :: 1 - Planning
Classifier: Environment :: Web Environment
Classifier: Framework :: Django
Classifier: Intended Audience :: Developers
Classifier: License :: OSI Approved :: MIT License
Classifier: Operating System :: OS Independent
Classifier: Programming Language :: Python
Classifier: Programming Language :: Python :: 2
Classifier: Programming Language :: Python :: 3
Classifier: Topic :: Internet :: WWW/HTTP
Classifier: Topic :: Software Development :: Libraries :: Python Modules
